apiendpoints/__init__.py
apiendpoints/client.py
apiendpoints/tests.py
apiendpoints-0.9.3.dist-info/LICENSE
apiendpoints-0.9.3.dist-info/METADATA
apiendpoints-0.9.3.dist-info/WHEEL
apiendpoints-0.9.3.dist-info/top_level.txt
apiendpoints-0.9.3.dist-info/RECORD
