Metadata-Version: 2.1
Name: apiendpoints
Version: 0.9.3
Summary: Wraps Python Requests with an (even) easier to use programming model for accessing a REST API.
Home-page: https://github.com/sethlivingston/python-api-client
Author: Seth M. Livingston
Author-email: webdevbyseth@gmail.com
License: MIT
Platform: UNKNOWN
Classifier: License :: OSI Approved :: MIT License
Classifier: Programming Language :: Python :: 3
Classifier: Programming Language :: Python :: 3.7
Requires-Dist: requests
